setup.cfg
setup.py
bearfield/__init__.py
bearfield/connection.py
bearfield/cursor.py
bearfield/document.py
bearfield/encoders.py
bearfield/errors.py
bearfield/field.py
bearfield/meta.py
bearfield/query.py
bearfield/reference.py
bearfield/types.py
bearfield/utils.py
bearfield.egg-info/PKG-INFO
bearfield.egg-info/SOURCES.txt
bearfield.egg-info/dependency_links.txt
bearfield.egg-info/not-zip-safe
bearfield.egg-info/pbr.json
bearfield.egg-info/requires.txt
bearfield.egg-info/top_level.txt