Metadata-Version: 1.1
Name: bearfield
Version: 1.9.5
Summary: Small MongoDB object layer.
Home-page: https://github.com/WiFast/bearfield
Author: WiFast
Author-email: rgb@wifast.com
License: BSD-derived
Keywords: python mongodb
Platform: UNKNOWN
Classifier: Intended Audience :: Developers
Classifier: Programming Language :: Python
Classifier: Programming Language :: Python :: 2
Classifier: Programming Language :: Python :: 2.7
Classifier: License :: OSI Approved :: BSD License
Classifier: Topic :: Database
